rich_interactive/__init__.py
rich_interactive/interactive.py
rich_interactive/interactive_layout.py
rich_interactive/interactive_panel.py
rich_interactive/interactive_table.py
rich_interactive-0.6.0.dist-info/LICENSE
rich_interactive-0.6.0.dist-info/METADATA
rich_interactive-0.6.0.dist-info/WHEEL
rich_interactive-0.6.0.dist-info/RECORD
