Metadata-Version: 2.1
Name: rich_interactive
Version: 0.6.0
Summary: Extends the Rich library with interactive layouts and tables, allowing seamless navigation and interaction via keyboard shortcuts
License: MIT
Author: Krzysztof Szumny
Author-email: noisy.pl@gmail.com
Requires-Python: >=3.11,<4.0
Classifier: License :: OSI Approved :: MIT License
Classifier: Programming Language :: Python :: 3
Classifier: Programming Language :: Python :: 3.11
Classifier: Programming Language :: Python :: 3.12
Requires-Dist: rich (>=13.7.1,<14.0.0)
